{
    "academicYear": "2023-2024",
    "receivingInstitution": "California Polytechnic University, San Luis Obispo",
    "sendingInstitution": "Saddleback College",
    "major": "ARCHITECTURAL ENGINEERING, B.S.",
    "agreements": [
        {
            "receving": {
                "conjunction": null,
                "courses": [
                    {
                        "courseNumber": "ARCE106",
                        "courseTitle": "Introduction to Building Systems",
                        "courseUnits": "2.00"
                    }
                ]
            },
            "sending": {
                "conjunction": null,
                "courses": []
            }
        },
        {
            "receving": {
                "conjunction": null,
                "courses": [
                    {
                        "courseNumber": "ARCE211",
                        "courseTitle": "Structures I",
                        "courseUnits": "3.00"
                    }
                ]
            },
            "sending": {
                "conjunction": null,
                "courses": []
            }
        },
        {
            "receving": {
                "conjunction": null,
                "courses": [
                    {
                        "courseNumber": "ARCE212",
                        "courseTitle": "Structures II",
                        "courseUnits": "3.00"
                    }
                ]
            },
            "sending": {
                "conjunction": null,
                "courses": []
            }
        },
        {
            "receving": {
                "conjunction": "AND",
                "courses": [
                    {
                        "courseNumber": "ARCE211",
                        "courseTitle": "Structures I",
                        "courseUnits": "3.00"
                    },
                    {
                        "courseNumber": "ARCE212",
                        "courseTitle": "Structures II",
                        "courseUnits": "3.00"
                    }
                ]
            },
            "sending": {
                "conjunction": null,
                "courses": []
            }
        },
        {
            "receving": {
                "conjunction": "AND",
                "courses": [
                    {
                        "courseNumber": "ARCE223",
                        "courseTitle": "Mechanics of Structural Members",
                        "courseUnits": "3.00"
                    },
                    {
                        "courseNumber": "ARCE224",
                        "courseTitle": "Mechanics of Structural Members Laboratory",
                        "courseUnits": "1.00"
                    }
                ]
            },
            "sending": {
                "conjunction": null,
                "courses": []
            }
        },
        {
            "receving": {
                "conjunction": null,
                "courses": [
                    {
                        "courseNumber": "ARCE227",
                        "courseTitle": "Structures III",
                        "courseUnits": "2.00"
                    }
                ]
            },
            "sending": {
                "conjunction": null,
                "courses": []
            }
        },
        {
            "receving": {
                "conjunction": null,
                "courses": [
                    {
                        "courseNumber": "ARCE257",
                        "courseTitle": "Structural CAD for Building Design",
                        "courseUnits": "2.00"
                    }
                ]
            },
            "sending": {
                "conjunction": null,
                "courses": []
            }
        },
        {
            "receving": {
                "conjunction": null,
                "courses": [
                    {
                        "courseNumber": "ME212",
                        "courseTitle": "Engineering Dynamics",
                        "courseUnits": "3.00"
                    }
                ]
            },
            "sending": {
                "conjunction": null,
                "courses": []
            }
        },
        {
            "receving": {
                "conjunction": "AND",
                "courses": [
                    {
                        "courseNumber": "ARCH131",
                        "courseTitle": "Design and Visual Communication 1.1",
                        "courseUnits": "4.00"
                    },
                    {
                        "courseNumber": "ARCH132",
                        "courseTitle": "Design and Visual Communication 1.2",
                        "courseUnits": "4.00"
                    },
                    {
                        "courseNumber": "ARCH133",
                        "courseTitle": "Design and Visual Communication 1.3",
                        "courseUnits": "4.00"
                    }
                ]
            },
            "sending": {
                "conjunction": null,
                "courses": []
            }
        },
        {
            "receving": {
                "conjunction": null,
                "courses": [
                    {
                        "courseNumber": "BRAE237",
                        "courseTitle": "Introduction to Engineering Surveying",
                        "courseUnits": "2.00"
                    }
                ]
            },
            "sending": {
                "conjunction": null,
                "courses": []
            }
        },
        {
            "receving": {
                "conjunction": null,
                "courses": [
                    {
                        "courseNumber": "CHEM124",
                        "courseTitle": "General Chemistry for Physical Science and Engineering I",
                        "courseUnits": "4.00"
                    }
                ]
            },
            "sending": {
                "conjunction": null,
                "courses": [
                    {
                        "courseNumber": "CHEM1A",
                        "courseTitle": "General Chemistry",
                        "courseUnits": "5.00"
                    }
                ]
            }
        },
        {
            "receving": {
                "conjunction": null,
                "courses": [
                    {
                        "courseNumber": "CM115",
                        "courseTitle": "Fundamentals of Construction Management",
                        "courseUnits": "6.00"
                    }
                ]
            },
            "sending": {
                "conjunction": null,
                "courses": []
            }
        },
        {
            "receving": {
                "conjunction": null,
                "courses": [
                    {
                        "courseNumber": "CM232",
                        "courseTitle": "Evaluation of Cost Alternatives",
                        "courseUnits": "3.00"
                    }
                ]
            },
            "sending": {
                "conjunction": null,
                "courses": []
            }
        },
        {
            "receving": {
                "conjunction": null,
                "courses": [
                    {
                        "courseNumber": "CSC231",
                        "courseTitle": "Programming for Engineering Students",
                        "courseUnits": "2.00"
                    }
                ]
            },
            "sending": {
                "conjunction": null,
                "courses": []
            }
        },
        {
            "receving": {
                "conjunction": null,
                "courses": [
                    {
                        "courseNumber": "EE201",
                        "courseTitle": "Electric Circuit Theory",
                        "courseUnits": "3.00"
                    }
                ]
            },
            "sending": {
                "conjunction": null,
                "courses": []
            }
        },
        {
            "receving": {
                "conjunction": null,
                "courses": [
                    {
                        "courseNumber": "GEOL201",
                        "courseTitle": "Physical Geology",
                        "courseUnits": "3.00"
                    }
                ]
            },
            "sending": {
                "conjunction": null,
                "courses": [
                    {
                        "courseNumber": "GEOL1",
                        "courseTitle": "Introduction to Physical Geology",
                        "courseUnits": "4.00"
                    }
                ]
            }
        },
        {
            "receving": {
                "conjunction": null,
                "courses": [
                    {
                        "courseNumber": "MATH141",
                        "courseTitle": "Calculus I",
                        "courseUnits": "4.00"
                    }
                ]
            },
            "sending": {
                "conjunction": null,
                "courses": [
                    {
                        "courseNumber": "MATH3A",
                        "courseTitle": "Analytic Geometry and Calculus",
                        "courseUnits": "5.00"
                    }
                ]
            }
        },
        {
            "receving": {
                "conjunction": null,
                "courses": [
                    {
                        "courseNumber": "MATH142",
                        "courseTitle": "Calculus II",
                        "courseUnits": "4.00"
                    }
                ]
            },
            "sending": {
                "conjunction": null,
                "courses": [
                    {
                        "courseNumber": "MATH3B",
                        "courseTitle": "Analytic Geometry and Calculus",
                        "courseUnits": "5.00"
                    }
                ]
            }
        },
        {
            "receving": {
                "conjunction": null,
                "courses": [
                    {
                        "courseNumber": "MATH143",
                        "courseTitle": "Calculus III",
                        "courseUnits": "4.00"
                    }
                ]
            },
            "sending": {
                "conjunction": null,
                "courses": [
                    {
                        "courseNumber": "MATH3B",
                        "courseTitle": "Analytic Geometry and Calculus",
                        "courseUnits": "5.00"
                    }
                ]
            }
        },
        {
            "receving": {
                "conjunction": null,
                "courses": [
                    {
                        "courseNumber": "MATH241",
                        "courseTitle": "Calculus IV",
                        "courseUnits": "4.00"
                    }
                ]
            },
            "sending": {
                "conjunction": null,
                "courses": [
                    {
                        "courseNumber": "MATH3C",
                        "courseTitle": "Analytic Geometry and Calculus",
                        "courseUnits": "5.00"
                    }
                ]
            }
        },
        {
            "receving": {
                "conjunction": null,
                "courses": [
                    {
                        "courseNumber": "MATH244",
                        "courseTitle": "Linear Analysis I",
                        "courseUnits": "4.00"
                    }
                ]
            },
            "sending": {
                "conjunction": "AND",
                "courses": [
                    {
                        "courseNumber": "MATH24",
                        "courseTitle": "Elementary Differential Equations",
                        "courseUnits": "4.00"
                    },
                    {
                        "courseNumber": "MATH26",
                        "courseTitle": "Introduction to Linear Algebra",
                        "courseUnits": "4.00"
                    }
                ]
            }
        },
        {
            "receving": {
                "conjunction": "AND",
                "courses": [
                    {
                        "courseNumber": "MATH141",
                        "courseTitle": "Calculus I",
                        "courseUnits": "4.00"
                    },
                    {
                        "courseNumber": "MATH142",
                        "courseTitle": "Calculus II",
                        "courseUnits": "4.00"
                    }
                ]
            },
            "sending": {
                "conjunction": "AND",
                "courses": [
                    {
                        "courseNumber": "MATH3A",
                        "courseTitle": "Analytic Geometry and Calculus",
                        "courseUnits": "5.00"
                    },
                    {
                        "courseNumber": "MATH3B",
                        "courseTitle": "Analytic Geometry and Calculus",
                        "courseUnits": "5.00"
                    }
                ]
            }
        },
        {
            "receving": {
                "conjunction": "AND",
                "courses": [
                    {
                        "courseNumber": "MATH141",
                        "courseTitle": "Calculus I",
                        "courseUnits": "4.00"
                    },
                    {
                        "courseNumber": "MATH142",
                        "courseTitle": "Calculus II",
                        "courseUnits": "4.00"
                    },
                    {
                        "courseNumber": "MATH143",
                        "courseTitle": "Calculus III",
                        "courseUnits": "4.00"
                    }
                ]
            },
            "sending": {
                "conjunction": "AND",
                "courses": [
                    {
                        "courseNumber": "MATH3A",
                        "courseTitle": "Analytic Geometry and Calculus",
                        "courseUnits": "5.00"
                    },
                    {
                        "courseNumber": "MATH3B",
                        "courseTitle": "Analytic Geometry and Calculus",
                        "courseUnits": "5.00"
                    }
                ]
            }
        },
        {
            "receving": {
                "conjunction": "AND",
                "courses": [
                    {
                        "courseNumber": "MATH141",
                        "courseTitle": "Calculus I",
                        "courseUnits": "4.00"
                    },
                    {
                        "courseNumber": "MATH142",
                        "courseTitle": "Calculus II",
                        "courseUnits": "4.00"
                    },
                    {
                        "courseNumber": "MATH143",
                        "courseTitle": "Calculus III",
                        "courseUnits": "4.00"
                    },
                    {
                        "courseNumber": "MATH241",
                        "courseTitle": "Calculus IV",
                        "courseUnits": "4.00"
                    }
                ]
            },
            "sending": {
                "conjunction": "AND",
                "courses": [
                    {
                        "courseNumber": "MATH3A",
                        "courseTitle": "Analytic Geometry and Calculus",
                        "courseUnits": "5.00"
                    },
                    {
                        "courseNumber": "MATH3B",
                        "courseTitle": "Analytic Geometry and Calculus",
                        "courseUnits": "5.00"
                    },
                    {
                        "courseNumber": "MATH3C",
                        "courseTitle": "Analytic Geometry and Calculus",
                        "courseUnits": "5.00"
                    }
                ]
            }
        },
        {
            "receving": {
                "conjunction": null,
                "courses": [
                    {
                        "courseNumber": "PHYS141",
                        "courseTitle": "General Physics I",
                        "courseUnits": "4.00"
                    }
                ]
            },
            "sending": {
                "conjunction": null,
                "courses": [
                    {
                        "courseNumber": "PHYS4A",
                        "courseTitle": "General Physics",
                        "courseUnits": "5.00"
                    }
                ]
            }
        },
        {
            "receving": {
                "conjunction": null,
                "courses": [
                    {
                        "courseNumber": "PHYS142",
                        "courseTitle": "General Physics II",
                        "courseUnits": "4.00"
                    }
                ]
            },
            "sending": {
                "conjunction": null,
                "courses": []
            }
        },
        {
            "receving": {
                "conjunction": null,
                "courses": [
                    {
                        "courseNumber": "PHYS143",
                        "courseTitle": "General Physics III",
                        "courseUnits": "4.00"
                    }
                ]
            },
            "sending": {
                "conjunction": null,
                "courses": [
                    {
                        "courseNumber": "PHYS4B",
                        "courseTitle": "General Physics",
                        "courseUnits": "5.00"
                    }
                ]
            }
        },
        {
            "receving": {
                "conjunction": "AND",
                "courses": [
                    {
                        "courseNumber": "PHYS141",
                        "courseTitle": "General Physics I",
                        "courseUnits": "4.00"
                    },
                    {
                        "courseNumber": "PHYS142",
                        "courseTitle": "General Physics II",
                        "courseUnits": "4.00"
                    }
                ]
            },
            "sending": {
                "conjunction": null,
                "courses": []
            }
        },
        {
            "receving": {
                "conjunction": "AND",
                "courses": [
                    {
                        "courseNumber": "PHYS141",
                        "courseTitle": "General Physics I",
                        "courseUnits": "4.00"
                    },
                    {
                        "courseNumber": "PHYS142",
                        "courseTitle": "General Physics II",
                        "courseUnits": "4.00"
                    },
                    {
                        "courseNumber": "PHYS143",
                        "courseTitle": "General Physics III",
                        "courseUnits": "4.00"
                    }
                ]
            },
            "sending": {
                "conjunction": "AND",
                "courses": [
                    {
                        "courseNumber": "PHYS4A",
                        "courseTitle": "General Physics",
                        "courseUnits": "5.00"
                    },
                    {
                        "courseNumber": "PHYS4C",
                        "courseTitle": "General Physics",
                        "courseUnits": "5.00"
                    },
                    {
                        "courseNumber": "PHYS4B",
                        "courseTitle": "General Physics",
                        "courseUnits": "5.00"
                    }
                ]
            }
        },
        {
            "receving": {
                "conjunction": null,
                "courses": [
                    {
                        "courseNumber": "ARCH217",
                        "courseTitle": "History of World Architecture: Prehistory- Middle Ages",
                        "courseUnits": "4.00"
                    }
                ]
            },
            "sending": {
                "conjunction": null,
                "courses": [
                    {
                        "courseNumber": "ARCH12",
                        "courseTitle": "History of Architecture",
                        "courseUnits": "3.00"
                    }
                ]
            }
        },
        {
            "receving": {
                "conjunction": null,
                "courses": [
                    {
                        "courseNumber": "ARCH218",
                        "courseTitle": "History of World Architecture: Middle Ages- 18th Century",
                        "courseUnits": "4.00"
                    }
                ]
            },
            "sending": {
                "conjunction": null,
                "courses": []
            }
        },
        {
            "receving": {
                "conjunction": null,
                "courses": [
                    {
                        "courseNumber": "ARCH219",
                        "courseTitle": "History of World Architecture: 18th Century- Present",
                        "courseUnits": "4.00"
                    }
                ]
            },
            "sending": {
                "conjunction": null,
                "courses": []
            }
        },
        {
            "receving": {
                "conjunction": null,
                "courses": [
                    {
                        "courseNumber": "ARCE260",
                        "courseTitle": "History of Structures",
                        "courseUnits": "4.00"
                    }
                ]
            },
            "sending": {
                "conjunction": null,
                "courses": []
            }
        }
    ]
}