{
    "0": {
        "courses": []
    },
    "1": {
        "courses": [
            {
                "conjunction": "OR",
                "courses": [
                    {
                        "courseNumber": "COMMST100",
                        "courseTitle": "Elements of Public Speaking",
                        "courseUnits": "3.00"
                    },
                    {
                        "courseNumber": "COMMST100H",
                        "courseTitle": "Elements of Public Speaking - Honors",
                        "courseUnits": "3.00"
                    }
                ],
                "subject": "COMS",
                "uniqueClass": true
            },
            {
                "courses": [],
                "note": "No articulation agreement found for HLTH101."
            },
            {
                "subject": "Health Issues",
                "course": [
                    {
                        "conjunction": null,
                        "courses": []
                    },
                    {
                        "conjunction": null,
                        "courses": []
                    }
                ],
                "uniqueClass": true,
                "customDesc": "Choose one of the following: HLTH255 or HLTH260."
            },
            {
                "subject": "General Psychology",
                "course": [
                    {
                        "conjunction": "OR",
                        "courses": [
                            {
                                "courseNumber": "PSYCH100",
                                "courseTitle": "General Psychology",
                                "courseUnits": "3.00"
                            },
                            {
                                "courseNumber": "PSYCH100H",
                                "courseTitle": "General Psychology - Honors",
                                "courseUnits": "3.00"
                            }
                        ]
                    },
                    {
                        "conjunction": "OR",
                        "courses": [
                            {
                                "courseNumber": "PSYCH100",
                                "courseTitle": "General Psychology",
                                "courseUnits": "3.00"
                            },
                            {
                                "courseNumber": "PSYCH100H",
                                "courseTitle": "General Psychology - Honors",
                                "courseUnits": "3.00"
                            }
                        ]
                    }
                ],
                "uniqueClass": true,
                "customDesc": "Choose one of the following: PSY201 or PSY202."
            }
        ]
    },
    "2": {
        "courses": [
            {
                "conjunction": null,
                "courses": [
                    {
                        "courseNumber": "CHEM150",
                        "courseTitle": "General Chemistry I",
                        "courseUnits": "5.00"
                    }
                ],
                "subject": "CHEM",
                "uniqueClass": false
            },
            {
                "conjunction": "OR",
                "courses": [
                    {
                        "courseNumber": "MATH108",
                        "courseTitle": "Statistics",
                        "courseUnits": "4.00"
                    },
                    {
                        "courseNumber": "PSYCH108",
                        "courseTitle": "Statistics",
                        "courseUnits": "4.00"
                    },
                    {
                        "courseNumber": "MATH110",
                        "courseTitle": "Introduction to Probability and Statistics",
                        "courseUnits": "4.00"
                    }
                ],
                "subject": "STAT",
                "uniqueClass": false
            },
            {
                "conjunction": null,
                "courses": [
                    {
                        "courseNumber": "ENGL101",
                        "courseTitle": "Freshman Composition",
                        "courseUnits": "4.00"
                    }
                ],
                "subject": "ENGL",
                "uniqueClass": false
            },
            {
                "courses": [],
                "note": "No articulation agreement found for HLTH265."
            }
        ]
    },
    "3": {
        "courses": [
            {
                "conjunction": "OR",
                "courses": [
                    {
                        "courseNumber": "BIOL130",
                        "courseTitle": "Cell and Molecular Biology",
                        "courseUnits": "4.00"
                    },
                    {
                        "courseNumber": "BIOL130H",
                        "courseTitle": "Cell and Molecular Biology - Honors",
                        "courseUnits": "4.00"
                    }
                ],
                "subject": "BIO",
                "uniqueClass": true
            },
            {
                "conjunction": null,
                "courses": [
                    {
                        "courseNumber": "COMMST125",
                        "courseTitle": "Critical Thinking through Argumentation and Debate",
                        "courseUnits": "3.00"
                    }
                ],
                "subject": "COMS",
                "uniqueClass": true
            },
            {
                "subject": "Choose One",
                "course": [
                    {
                        "conjunction": "OR",
                        "courses": [
                            {
                                "courseNumber": "ANTHRO102",
                                "courseTitle": "Cultural Anthropology",
                                "courseUnits": "3.00"
                            },
                            {
                                "courseNumber": "ANTHRO102H",
                                "courseTitle": "Cultural Anthropology - Honors",
                                "courseUnits": "3.00"
                            }
                        ]
                    },
                    {
                        "conjunction": null,
                        "courses": [
                            {
                                "courseNumber": "SOC100",
                                "courseTitle": "Introduction to Sociology",
                                "courseUnits": "3.00"
                            }
                        ]
                    }
                ],
                "uniqueClass": true,
                "customDesc": "Choose one of the following: ANT201 or SOC110."
            }
        ]
    },
    "5": {
        "courses": [
            {
                "conjunction": null,
                "courses": [
                    {
                        "courseNumber": "HEALTH263",
                        "courseTitle": "Nutrition and Health",
                        "courseUnits": "3.00"
                    }
                ],
                "subject": "FSN",
                "uniqueClass": true
            },
            {
                "courses": [],
                "note": "No articulation agreement found for HLTH298."
            },
            {
                "subject": "Microbiology",
                "course": [
                    {
                        "conjunction": "OR",
                        "courses": [
                            {
                                "courseNumber": "MICRO102",
                                "courseTitle": "Introductory Microbiology",
                                "courseUnits": "4.00"
                            },
                            {
                                "courseNumber": "MICRO150",
                                "courseTitle": "Medical Microbiology",
                                "courseUnits": "5.00"
                            }
                        ]
                    },
                    {
                        "conjunction": null,
                        "courses": [
                            {
                                "courseNumber": "MICRO150",
                                "courseTitle": "Medical Microbiology",
                                "courseUnits": "5.00"
                            }
                        ]
                    }
                ],
                "uniqueClass": true,
                "customDesc": "Choose one of the following: MCRO221 or MCRO224."
            },
            {
                "subject": "GE",
                "course": null,
                "uniqueClass": true,
                "customDesc": "One course from each of the following GE areas must be completed: A1, A2, A3, C1, C2, Lower-Division C Elective, Upper-Division C, D1, Upper-Division D, F, and GE Elective. Upper-Division C and Upper-Division D should be taken only after Junior standing is reached (90 units). Refer to online catalog for GE course selection, United States Cultural Pluralism (USCP) and Graduation Writing Requirement (GWR). USCP requirement can be satisfied by some (but not all) courses within GE categories: Upper-Division B, C1, Upper-Division C, D1, D2, Upper-Division D, or E."
            }
        ]
    },
    "6": {
        "courses": [
            {
                "courses": [],
                "note": "No articulation agreement found for BIO231."
            },
            {
                "subject": "Communication",
                "course": [
                    null,
                    null
                ],
                "uniqueClass": true,
                "customDesc": "Choose one of the following: COMS301 or JOUR312."
            },
            {
                "subject": "GE",
                "course": null,
                "uniqueClass": true,
                "customDesc": "One course from each of the following GE areas must be completed: A1, A2, A3, C1, C2, Lower-Division C Elective, Upper-Division C, D1, Upper-Division D, F, and GE Elective. Upper-Division C and Upper-Division D should be taken only after Junior standing is reached (90 units). Refer to online catalog for GE course selection, United States Cultural Pluralism (USCP) and Graduation Writing Requirement (GWR). USCP requirement can be satisfied by some (but not all) courses within GE categories: Upper-Division B, C1, Upper-Division C, D1, D2, Upper-Division D, or E."
            }
        ]
    },
    "7": {
        "courses": [
            {
                "courses": [],
                "note": "No articulation agreement found for BIO232."
            },
            {
                "subject": "GE",
                "course": null,
                "uniqueClass": false,
                "customDesc": "One course from each of the following GE areas must be completed: A1, A2, A3, C1, C2, Lower-Division C Elective, Upper-Division C, D1, Upper-Division D, F, and GE Elective. Upper-Division C and Upper-Division D should be taken only after Junior standing is reached (90 units). Refer to online catalog for GE course selection, United States Cultural Pluralism (USCP) and Graduation Writing Requirement (GWR). USCP requirement can be satisfied by some (but not all) courses within GE categories: Upper-Division B, C1, Upper-Division C, D1, D2, Upper-Division D, or E."
            },
            {
                "subject": "Free Elective",
                "course": null,
                "uniqueClass": true,
                "customDesc": "Any Free Elective course can go here."
            }
        ]
    }
}