[
    {
        "major": "Administration, B.A. (Multiple Concentrations)",
        "key": 26789930
    },
    {
        "major": "Administration, B.A. - Business Analytics Concentration",
        "key": 26789925
    },
    {
        "major": "Administration, B.A. - Hospitality Management Concentration",
        "key": 26789924
    },
    {
        "major": "Administration, B.A. - Information Security Concentration",
        "key": 26789926
    },
    {
        "major": "Administration, B.A. - Information Systems and Technology Concentration",
        "key": 26789927
    },
    {
        "major": "Anthropology, B.A.",
        "key": 26789928
    },
    {
        "major": "Arabic Language, Literature, and Culture, B.A.",
        "key": 26789929
    },
    {
        "major": "Bioinformatics, B.S.",
        "key": 26789931
    },
    {
        "major": "Biology, B.S.",
        "key": 26789934
    },
    {
        "major": "Career and Technical Studies, B.A.",
        "key": 26789932
    },
    {
        "major": "Career and Technical Studies, B.S.",
        "key": 26789933
    },
    {
        "major": "Chemistry, B.A. - Biochemistry Concentration",
        "key": 26789935
    },
    {
        "major": "Chemistry, B.A. - Chemistry Concentration",
        "key": 26789936
    },
    {
        "major": "Chemistry, B.S. - Biochemistry Concentration",
        "key": 26789937
    },
    {
        "major": "Chemistry, B.S. - Chemistry Concentration",
        "key": 26789938
    },
    {
        "major": "Communication, B.A. - Media Studies Concentration",
        "key": 26789939
    },
    {
        "major": "Communication, B.A. - Relational and Organizational Communication Concentration",
        "key": 26789942
    },
    {
        "major": "Communication, B.A. - Strategic Communication Concentration",
        "key": 26789940
    },
    {
        "major": "Computer Engineering, B.S.",
        "key": 26789943
    },
    {
        "major": "Computer Science, B.S.",
        "key": 26789941
    },
    {
        "major": "Computer Systems, B.A.",
        "key": 26789944
    },
    {
        "major": "Criminal Justice, B.A.",
        "key": 26789945
    },
    {
        "major": "Economics, B.A. - Applied Economics Concentration",
        "key": 26789946
    },
    {
        "major": "Economics, B.A. - General Economics Concentration",
        "key": 26789947
    },
    {
        "major": "Economics, B.A. - Mathematical Economics Concentration",
        "key": 26789948
    },
    {
        "major": "English, B.A.",
        "key": 26789949
    },
    {
        "major": "Environmental Health Science, B.S.",
        "key": 26789951
    },
    {
        "major": "Environmental Studies, B.A. - Environmental Sustainability Concentration",
        "key": 26789950
    },
    {
        "major": "Environmental Studies, B.A. - Environmental Systems Concentration",
        "key": 26789955
    },
    {
        "major": "Ethnic Studies, B.A.",
        "key": 26789952
    },
    {
        "major": "French, B.A.",
        "key": 26789953
    },
    {
        "major": "Geography, B.A.",
        "key": 26789954
    },
    {
        "major": "Geology, B.A. - Field and Applied Geology Concentration",
        "key": 26789957
    },
    {
        "major": "Geology, B.A. - General Geology Concentration",
        "key": 26789956
    },
    {
        "major": "Geology, B.S. - Environmental Geology Concentration",
        "key": 26789959
    },
    {
        "major": "Geology, B.S. - General Geology Concentration",
        "key": 26789958
    },
    {
        "major": "Global Studies, B.A.",
        "key": 26789960
    },
    {
        "major": "Health Services Administration, B.S.",
        "key": 26789961
    },
    {
        "major": "History, B.A. - General Concentration",
        "key": 26789962
    },
    {
        "major": "History, B.A. - Pre-Credential Concentration",
        "key": 26789963
    },
    {
        "major": "Information Systems and Technology, B.S.",
        "key": 26789964
    },
    {
        "major": "Intelligence and Crime Analysis, B.S. - Cyber Security Concentration",
        "key": 26789965
    },
    {
        "major": "Intelligence and Crime Analysis, B.S. - Geographic Information Systems Concentration",
        "key": 26789966
    },
    {
        "major": "Intelligence and Crime Analysis, B.S. - Homeland Security Concentration",
        "key": 26789967
    },
    {
        "major": "Mathematics, B.A.",
        "key": 26789968
    },
    {
        "major": "Mathematics, B.S. - Applied Mathematics Concentration",
        "key": 26789970
    },
    {
        "major": "Mathematics, B.S. - General Mathematics Concentration",
        "key": 26789969
    },
    {
        "major": "Mathematics, B.S. - Teaching Mathematics Concentration",
        "key": 26789971
    },
    {
        "major": "Nursing, B.S.",
        "key": 26789972
    },
    {
        "major": "Nutritional Science and Dietetics, B.S.",
        "key": 26789973
    },
    {
        "major": "Philosophy, B.A.",
        "key": 26789974
    },
    {
        "major": "Physics, B.A.",
        "key": 26789976
    },
    {
        "major": "Physics, B.S.",
        "key": 26789975
    },
    {
        "major": "Political Economy, B.A.",
        "key": 26789978
    },
    {
        "major": "Political Science, B.A.",
        "key": 26789977
    },
    {
        "major": "Psychology, B.A.",
        "key": 26789979
    },
    {
        "major": "Public Health, B.S.",
        "key": 26789980
    },
    {
        "major": "Public History, B.A.",
        "key": 26789981
    },
    {
        "major": "Social Sciences, B.A.",
        "key": 26789982
    },
    {
        "major": "Social Work, B.A.",
        "key": 26789986
    },
    {
        "major": "Sociology, B.A.",
        "key": 26789983
    },
    {
        "major": "Spanish, B.A.",
        "key": 26789984
    },
    {
        "major": "Theatre Arts, B.A.",
        "key": 26789985
    }
]